src/fake_chat/__fake__.py
src/fake_chat/__init__.py
fake_chat-0.1.3.dist-info/METADATA
fake_chat-0.1.3.dist-info/WHEEL
fake_chat-0.1.3.dist-info/top_level.txt
fake_chat-0.1.3.dist-info/RECORD
