Metadata-Version: 2.1
Name: fake-chat
Version: 0.1.3
Home-page: https://github.com/Aurorax-own/fake_chat
Author: Aurorax-own
Author-email: 15047150695@163.com
Project-URL: Source, https://github.com/Aurorax-own/fake_chat
Project-URL: Tracker, https://github.com/Aurorax-own/fake_chat/issues
Requires-Dist: pandora-chatgpt ==1.3.0
Requires-Dist: requests ==2.31.0
